imaris_cooker/__init__.py
imaris_cooker/ims_to_tiff.py
imaris_cooker-0.1.1.dist-info/METADATA
imaris_cooker-0.1.1.dist-info/WHEEL
imaris_cooker-0.1.1.dist-info/entry_points.txt
imaris_cooker-0.1.1.dist-info/top_level.txt
imaris_cooker-0.1.1.dist-info/RECORD
