Metadata-Version: 2.2
Name: imaris-cooker
Version: 0.1.1
Summary: A tool for converting IMS format images to TIFF format
Author: Guanhao Sun
License: MIT
Classifier: Development Status :: 3 - Alpha
Classifier: Intended Audience :: Science/Research
Classifier: License :: OSI Approved :: MIT License
Classifier: Programming Language :: Python :: 3
Classifier: Programming Language :: Python :: 3.7
Classifier: Programming Language :: Python :: 3.8
Classifier: Programming Language :: Python :: 3.9
Classifier: Programming Language :: Python :: 3.10
Classifier: Topic :: Scientific/Engineering :: Image Processing
Requires-Python: >=3.7
Requires-Dist: h5py
Requires-Dist: numpy
Requires-Dist: tifffile
Requires-Dist: tqdm
Dynamic: requires-python
